claude_notes/__init__.py
claude_notes/__main__.py
claude_notes/cli.py
claude_notes/pager.py
claude_notes/parser.py
claude_notes/formatters/__init__.py
claude_notes/formatters/animated.py
claude_notes/formatters/base.py
claude_notes/formatters/factory.py
claude_notes/formatters/html.py
claude_notes/formatters/terminal.py
claude_notes/formatters/tools.py
claude_notes-0.1.8.dist-info/METADATA
claude_notes-0.1.8.dist-info/WHEEL
claude_notes-0.1.8.dist-info/entry_points.txt
claude_notes-0.1.8.dist-info/licenses/LICENSE
claude_notes-0.1.8.dist-info/RECORD
