Metadata-Version: 2.4
Name: claude-notes
Version: 0.1.8
Summary: Transform Claude Code transcript JSONL files to terminal and HTML views
Project-URL: Homepage, https://github.com/vtemian/claude-notes
Project-URL: Repository, https://github.com/vtemian/claude-notes
Project-URL: Issues, https://github.com/vtemian/claude-notes/issues
Project-URL: Documentation, https://github.com/vtemian/claude-notes#readme
Author: Claude Notes Contributors
License: MIT
License-File: LICENSE
Keywords: ai,claude,cli,html,terminal,transcript
Classifier: Development Status :: 4 - Beta
Classifier: Environment :: Console
Classifier: Intended Audience :: Developers
Classifier: License :: OSI Approved :: MIT License
Classifier: Operating System :: OS Independent
Classifier: Programming Language :: Python :: 3
Classifier: Programming Language :: Python :: 3.11
Classifier: Programming Language :: Python :: 3.12
Classifier: Topic :: Software Development
Classifier: Topic :: Text Processing :: Markup :: HTML
Classifier: Topic :: Utilities
Requires-Python: >=3.11
Requires-Dist: click>=8.1.0
Requires-Dist: rich>=13.7.0
Provides-Extra: animation
Requires-Dist: asciinema>=2.3.0; extra == 'animation'
Provides-Extra: dev
Requires-Dist: pytest-cov>=4.0.0; extra == 'dev'
Requires-Dist: pytest>=7.0.0; extra == 'dev'
Requires-Dist: ruff>=0.1.0; extra == 'dev'
